{
  "users": {
    "160121042902188033": {
      "balance": 39998957,
      "inventory": [
        {
          "id": "ru_b_plushie",
          "count": 1,
          "owned": 1
        },
        {
          "id": "skull",
          "count": 1,
          "owned": 1
        }
      ]
    }
  },
  "guilds": {
    "844038368920076329": {
      "pinboard": {
        "channel": "844308393678077972",
        "emoji": {
          "unicode": "📌"
        },
        "minReacts": 1,
        "enabled": true,
        "cache": [
          "995155988829175869"
        ]
      }
    }
  },
  "jnfr": {
    "pot": 185
  }
}